SuperHelper/__init__.py
SuperHelper/Core/__init__.py
SuperHelper/Core/core_cli.py
SuperHelper/Core/core_commands.py
SuperHelper/Core/core_loader.py
SuperHelper/Core/Config/__init__.py
SuperHelper/Core/Config/app_config.py
SuperHelper/Core/Config/config_class.py
SuperHelper/Core/Utils/__init__.py
SuperHelper/Core/Utils/bit_ops.py
SuperHelper/Core/Utils/crypto_ops.py
SuperHelper/Core/Utils/file_ops.py
SuperHelper/Core/Utils/logger.py
SuperHelper/Core/Utils/type_ensure.py
SuperHelper/Core/Utils/type_hinting.py
SuperHelper/Modules/__init__.py
SuperHelper/Modules/CovidTracker/__init__.py
SuperHelper/Modules/CovidTracker/__main__.py
SuperHelper/Modules/CovidTracker/req.json
SuperHelper/Modules/FocusEnabler/__init__.py
SuperHelper/Modules/FocusEnabler/__main__.py
SuperHelper/Modules/Stenographer/__init__.py
SuperHelper/Modules/Stenographer/__main__.py
SuperHelper/Modules/Stenographer/req.json
SuperHelper-1.2.0.dist-info/LICENSE
SuperHelper-1.2.0.dist-info/METADATA
SuperHelper-1.2.0.dist-info/WHEEL
SuperHelper-1.2.0.dist-info/entry_points.txt
SuperHelper-1.2.0.dist-info/top_level.txt
SuperHelper-1.2.0.dist-info/RECORD
