Metadata-Version: 2.1
Name: SuperHelper
Version: 1.2.0
Summary: A collection of Python CLI to make life easier for terminal geeks!
Home-page: https://github.com/GreaterGoodCorp/FocusEnabler
Author: Nguyen Thai Binh
Author-email: binhnt.mdev@gmail.com
License: UNKNOWN
Project-URL: Bug Tracker, https://github.com/GreaterGoodCorp/FocusEnabler/issues
Platform: UNKNOWN
Classifier: Development Status :: 5 - Production/Stable
Classifier: Environment :: Console
Classifier: Intended Audience :: Developers
Classifier: Intended Audience :: End Users/Desktop
Classifier: License :: OSI Approved :: MIT License
Classifier: Natural Language :: English
Classifier: Operating System :: MacOS
Classifier: Operating System :: POSIX
Classifier: Operating System :: POSIX :: Linux
Classifier: Programming Language :: Python :: 3.9
Classifier: Topic :: Home Automation
Classifier: Topic :: Office/Business
Classifier: Topic :: Utilities
Requires-Python: >=3.6
Requires-Dist: click
Requires-Dist: cryptography
